nprompter/__init__.py
nprompter/__main__.py
nprompter/api/__init__.py
nprompter/api/notion_client.py
nprompter/cli/__init__.py
nprompter/cli/defaults.py
nprompter/cli/helpers.py
nprompter/cli/output.py
nprompter/processing/__init__.py
nprompter/processing/processor.py
nprompter/web/__init__.py
nprompter/web/assets/app.js
nprompter/web/assets/apple-touch-icon.png
nprompter/web/assets/favicon-96x96.png
nprompter/web/assets/favicon.ico
nprompter/web/assets/favicon.svg
nprompter/web/assets/images/icons/icon-128x128.png
nprompter/web/assets/images/icons/icon-144x144.png
nprompter/web/assets/images/icons/icon-152x152.png
nprompter/web/assets/images/icons/icon-192x192.png
nprompter/web/assets/images/icons/icon-384x384.png
nprompter/web/assets/images/icons/icon-512x512.png
nprompter/web/assets/images/icons/icon-72x72.png
nprompter/web/assets/images/icons/icon-96x96.png
nprompter/web/nprompter.toml
nprompter/web/templates/base.html
nprompter/web/templates/database_index.html
nprompter/web/templates/global_index.html
nprompter/web/templates/manifest.json
nprompter/web/templates/nprompter.css
nprompter/web/templates/script.html
nprompter/web/templates/service-worker.js
nprompter/web/templates/settings.js
nprompter-4.4.0.dist-info/WHEEL
nprompter-4.4.0.dist-info/entry_points.txt
nprompter-4.4.0.dist-info/METADATA
nprompter-4.4.0.dist-info/RECORD
