Metadata-Version: 2.4
Name: nprompter
Version: 4.4.0
Summary: A web based teleprompter that uses Notion as a storage backend
Author: Antonio Feregrino
Author-email: Antonio Feregrino <antonio.feregrino@gmail.com>
License-Expression: MIT
Requires-Dist: jinja2>=3.1.6
Requires-Dist: python-slugify>=8.0.4
Requires-Dist: requests>=2.32.5
Requires-Dist: tomli>=2.2.1
Requires-Dist: typer>=0.19.2
Requires-Python: >=3.11
